MANIFEST.in
README.rst
setup.py
AppInst.egg-info/PKG-INFO
AppInst.egg-info/SOURCES.txt
AppInst.egg-info/dependency_links.txt
AppInst.egg-info/not-zip-safe
AppInst.egg-info/top_level.txt
appinst/__init__.py
appinst/darwin.py
appinst/freedesktop.py
appinst/linux2.py
appinst/resource.h
appinst/win32.py
appinst/wininst.c