Metadata-Version: 1.0
Name: AppInst
Version: 2.1.5
Summary: cross platform APIs to install applications menu items
Home-page: UNKNOWN
Author: Enthought, Inc.
Author-email: info@enthought.com
License: BSD
Platform: UNKNOWN
